{"name": "Ourlog", "token": null, "intro": "Decentralized communication tool for communities", "links": [{"title": "Website", "url": "https://www.ourlog.xyz/"}, {"title": "Twitter", "url": "relationalorg"}], "introduce": "Ourlog is a decentralized communication tool for communities to log their research, thinking, and insights in a collective environment for the purposes of publishing. From scientific research, to government, to social groups, to web3 builders, Ourlog is a public, networked goods tool for any team to cohere and publish its collective intelligence."}