{"name": "Gem", "token": null, "intro": "NFT aggregator", "links": [{"title": "Website", "url": "https://www.gem.xyz/"}, {"title": "Twitter", "url": "gemxyz"}, {"title": "Discord", "url": "https://discord.com/invite/gemxyz"}], "introduce": "gem.xyz is an NFT aggregator helps users to buy NFTs across multiple marketplaces in a single transaction, pay with any ERC-20 token rather than spending their ETH and view analytics such as sales volume, floor prices, and rarity-based ranking for NFT collections."}