{"name": "Specular", "token": null, "intro": "An optimistic rollup that is EVM-native", "links": [{"title": "Website", "url": "https://specular.network/"}, {"title": "Twitter", "url": "SpecularL2"}, {"title": "Medium", "url": "https://medium.com/@SpecularL2/"}], "introduce": "Specular is the first EVM-native optimistic rollup, and provides stronger security and decentralization properties than existing optimistic rollup solutions. Specular achieves: (1) a minimal trusted computing base, improving security, auditability and upgradeability; (2) support for permissionless, trust-minimized participation of multiple Ethereum clients, enabling client diversity; and (3) efficient dispute resolution."}