{"name": "Neo", "token": "NEO", "intro": "A public chain for building decentralized applications", "links": [{"title": "Website", "url": "https://neo.org/"}, {"title": "Twitter", "url": "neo_blockchain"}, {"title": "Telegram", "url": "https://t.me/NEO_EN"}, {"title": "Github", "url": "https://github.com/neo-project/neo"}, {"title": "Medium", "url": "https://medium.com/neo-smart-economy"}, {"title": "CMC", "url": "https://coinmarketcap.com/currencies/neo/"}], "introduce": "Neo is an open-source community driven blockchain platform, which is a blockchain platform for building decentralized applications. Neo enables developers to digitize and automate the management of assets through smart contracts. It also provides powerful native infrastructures such as decentralized storage, oracles, and domain name service, creating a solid foundation for the Next-Gen Internet."}