{"name": "SHIELD PROTOCOL", "token": "SHIELD", "intro": "First 2FA on the Blockchain", "links": [{"title": "Website", "url": "https://shieldprotocol.org/"}, {"title": "Twitter", "url": "shield2protocol"}], "introduce": "Shield Protocol is First 2FA on Blockchain which integrates 2FA backup with BNB Chain, Polygon, Fantom Opera & WANCHAIN Mainnets. Users can backup and restore their 2FA accounts on these chains rather than centralised servers, which also facilitate NO personal data collection of users."}