{"name": "Utopo", "token": null, "intro": "One-Stop GameFi Service Platform", "links": [{"title": "Website", "url": "https://www.utopo.com/"}, {"title": "Twitter", "url": "utopogame"}, {"title": "Gitbook", "url": "https://utopo.gitbook.io/"}], "introduce": "Utopo is a metaverse game recommendation platform and it is a new GameFi player community that integrates SocialFi. Players can enjoy one-stop services such as downloads, purchases, news, walkthroughs, and social networking here. Besides, players can discover more good games via sharing latest industry trends with other players."}