{"name": "Popsicle Finance", "token": "ICE", "intro": "Multichain yield optimization platform for Liquidity Providers", "links": [{"title": "Website", "url": "https://popsicle.finance/"}, {"title": "Twitter", "url": "PopsicleFinance"}, {"title": "Telegram", "url": "https://t.me/PopsicleFinance"}, {"title": "Github", "url": "https://github.com/Popsicle-Finance/Contracts"}, {"title": "CMC", "url": "https://coinmarketcap.com/currencies/popsicle-finance/"}], "introduce": "Popsicle Finance is a multichain yield optimization platform for Liquidity Providers. Popsicle Finance manages liquidity across multiple chains in order to increase capital efficiency and automatically provide its users with the highest possible yield on the assets they wish to deploy to liquidity pools."}