{"name": "Mesa", "token": null, "intro": "Batch auction DEX", "links": [{"title": "Website", "url": "https://mesa.eth.limo/"}], "introduce": "Mesa is a decentralized application built on the Gnosis Protocol, a fully permissionless DEX that enables ring trades to maximize liquidity. Gnosis Protocol enables ring trades to maximize liquidity. Ring trades are order settlements which share liquidity across all orders, rather than a single token pair, and uniquely suited for trading prediction market tokens and the long tail of all tokenized assets."}