{"name": "Pirate Chain", "token": "ARRR", "intro": "Decentralized blockchain focused on user privacy", "links": [{"title": "Website", "url": "https://pirate.black/"}, {"title": "Twitter", "url": "PirateChain"}, {"title": "Discord", "url": "https://discord.com/invite/sqrCJce"}, {"title": "Telegram", "url": "https://t.me/piratechain"}, {"title": "Github", "url": "https://github.com/PirateNetwork"}, {"title": "White Paper", "url": "https://pirate.black/whitepaper"}, {"title": "Medium", "url": "https://medium.com/piratechain"}, {"title": "CMC", "url": "https://coinmarketcap.com/currencies/pirate-chain/"}], "introduce": "Pirate Chain is a private, decentralized blockchain that uses zk-SNARKs to shield 100% of the peer-to-peer transactions on the blockchain making for highly anonymous and private transactions."}