{"name": "Nifty's", "token": null, "intro": "Collect eco-friendly NFTs from your favorite brands and creators", "links": [{"title": "Website", "url": "https://niftys.com/"}, {"title": "Twitter", "url": "niftys"}, {"title": "Discord", "url": "https://discord.gg/niftys"}, {"title": "Medium", "url": "https://niftys.medium.com/"}], "introduce": "Nifty's is an NFT-focused social media platform that brings together premium publishers, brands and creators with collectors, curators and the communities of fans that will emerge around them. Offering an easy-to-use interface, the innovative platform will allow members to create, collect, discover, and curate the most important digital art and other collectables from across the scattered NFT universe. Leveraging MEME Protocol's technology, Nifty's will provide creators with a premium, powerful, flexible and safe platform to launch their NFTs."}