{"name": "BTCST", "token": "BTCST", "intro": "Protocol to Tokenize Bitcoin Standard Hashrate", "links": [{"title": "Website", "url": "https://www.btcst.finance"}, {"title": "Twitter", "url": "BTCST2020"}, {"title": "Telegram", "url": "https://t.me/BTCST_Community_EN"}, {"title": "Medium", "url": "https://btcst.medium.com/"}, {"title": "CMC", "url": "https://coinmarketcap.com/currencies/btc-standard-hashrate-token/"}], "introduce": "BTCST is a protocol that tokenizes Bitcoin\u2019s standard Hashrate, with the goal of expanding and opening Bitcoin\u2019s mining market."}