{"name": "Nealthy", "token": null, "intro": "on-chain index products", "links": [{"title": "Website", "url": "https://www.nealthy.com/"}, {"title": "Twitter", "url": "nealthy_xyz"}], "introduce": "Nealthy provides ETF and index-like funds for the digital asset investor that enable investors to enter Web3 markets quickly and worry-free. Index tokens replicate the structure of classic exchange-traded funds (ETFs) by storing multiple digital assets onchain, diversifying the portfolio in case of unexpected market shifts. "}