{"name": "Callisto Network", "token": "CLO", "intro": "Layer 1 Ethereum compatible smart contract solution", "links": [{"title": "Website", "url": "https://callisto.network/"}, {"title": "Twitter", "url": "CallistoSupport"}, {"title": "Discord", "url": "https://discordapp.com/invite/fGdPSA2"}, {"title": "LinkedIn", "url": "https://www.linkedin.com/company/callisto-network/"}, {"title": "CoinGecko", "url": "https://www.coingecko.com/en/coins/callisto-network"}], "introduce": "Callisto Network is a layer 1 Ethereum compatible smart contract solution based on a proof-of-work blockchain. Powered by its native cryptocurrency, CLO, Callisto Network is fast, safe, allows for low-cost transactions, and is protected against 51% attacks."}