{"name": "Biswap", "token": "BSW", "intro": "Decentralized exchange platform", "links": [{"title": "Website", "url": "https://biswap.org/"}, {"title": "Twitter", "url": "Biswap_DEX"}, {"title": "Telegram", "url": "https://t.me/biswap_news"}, {"title": "Github", "url": "https://github.com/biswap-org"}, {"title": "Medium", "url": "https://biswap-dex.medium.com/"}, {"title": "CMC", "url": "https://coinmarketcap.com/currencies/biswap/"}], "introduce": "Biswap is a decentralized exchange platform and uses an automated market maker (AMM) model to fulfill orders. Biswap gives its users a chance to exchange BEP-20 tokens, provide liquidity and earn passive income in return, stake tokens in Farms and Launchpools as well as earn referral rewards."}