{"name": "Request Network", "token": "REQ", "intro": "The protocol for payment requests", "links": [{"title": "Website", "url": "https://request.network/"}, {"title": "Twitter", "url": "requestnetwork"}, {"title": "Telegram", "url": "https://t.me/requestnetwork"}, {"title": "Github", "url": "https://github.com/RequestNetwork/"}, {"title": "Blog", "url": "https://blog.request.network/"}, {"title": "CMC", "url": "https://coinmarketcap.com/currencies/request/"}], "introduce": "Request is an open and unique database for payment requests including invoices or individual payment requests. The Request Protocol is the core of Request. It's the bottom layer that defines and handles the data of a request and persists them to a distributed ledger to make Request open, trustless, secure and resilient.\u00a0Crypto organizations & freelancers can use Request App for invoices, expenses, payroll, and accounting."}