{"name": "Yuliverse", "token": "ART", "intro": "Real World Seek-to-Earn Metaverse", "links": [{"title": "Website", "url": "https://www.yuliverse.com/"}, {"title": "Twitter", "url": "TheYuliverse"}, {"title": "Discord", "url": "https://discord.com/invite/Yuliverseofficial"}], "introduce": "Yuliverse is an alternative reality metaverse which is parallel to the real world and bring players a new lifestyle. Meanwhile, it's also a game-based social application. Yuliverse currently has thousands of fantastic and exciting story lines. By participating in role-playing, players can obtain $ARG and $ART by accomplishing quests."}