{"name": "SYNTHR", "token": null, "intro": "Synthetic asset protocol", "links": [{"title": "Website", "url": "https://www.synthr.io/"}, {"title": "Twitter", "url": "synthr_defi"}, {"title": "Discord", "url": "https://discord.gg/KkUzFPanf5"}, {"title": "Telegram", "url": "https://t.me/synthrcommunitychannel"}, {"title": "Github", "url": "https://github.com/synthrio"}, {"title": "White Paper", "url": "https://www.synthr.io/static/docs/Synthr_WP.pdf"}, {"title": "Medium", "url": "https://medium.com/@Synthr"}], "introduce": "SYNTHR is a synthetic asset protocol that enables users to mint and trade on-chain derivatives of various financial assets using trustless financial contracts. The protocol uses the Global Debt Model to mint syAssets, which can then be used to interact with an entire ecosystem of modules to perform various functions such as access to capital-efficient multi-chain liquidity, slippage-free swaps, real and sustainable farming, and safe bridging. "}