{"name": "Eykar", "token": null, "intro": "A decentralized strategy game", "links": [{"title": "Website", "url": "https://eykar.org/"}, {"title": "Twitter", "url": "Starknet_Intern"}, {"title": "Discord", "url": "https://starknet.io/discord"}, {"title": "Github", "url": "https://github.com/starkware-libs"}, {"title": "Medium", "url": "https://medium.com/starkware/starknet/home"}], "introduce": "Eykar is a decentralized game of conquest powered by blockchain. An almost infinite territory that can be conquered through alliances and wars."}