{"name": "Drips Protocol", "token": null, "intro": "Web3 protocol for NFT subscriptions and memberships", "links": [{"title": "Website", "url": "https://www.drips.network/"}, {"title": "Twitter", "url": "dripsnetwork"}, {"title": "Discord", "url": "https://discord.gg/zCjkTT4MnZ"}], "introduce": "Drips is a Web3 protocol for generating recurring income, with subscriptions and NFT memberships. Using Drips, creators & developers can issue monthly memberships and give their fans unique benefits in exchange for their recurring financial support. Using the permissionless financial infrastructure of Ethereum, Drips memberships are represented by Non-Fungible Tokens (NFTs). These memberships are available to anyone and can enable benefits across any application on the web that supports Ethereum (Discord, Telegram, Reddit, Snapshot, Radicle Upstream & many more)."}