{"name": "NFTX", "token": "NFTX", "intro": "The liquidity protocol for NFTs", "links": [{"title": "Website", "url": "https://nftx.org/"}, {"title": "Twitter", "url": "nftx_"}, {"title": "Discord", "url": "https://discord.com/invite/5ygF8rxdYR"}, {"title": "Github", "url": "https://github.com/NFTX-project/x-contracts"}, {"title": "Blog", "url": "https://blog.nftx.org/"}, {"title": "CMC", "url": "https://coinmarketcap.com/currencies/nftx/"}, {"title": "Forum", "url": "https://forum.nftx.org/"}], "introduce": "NFTX is a platform for creating liquid markets for illiquid Non-Fungible Tokens (NFTs). Users deposit their NFT into an NFTX vault and mint a fungible ERC20 token (vToken) that represents a claim on a random asset from within the vault. vTokens can also be used to redeem a specific NFT from a vault."}