{"name": "Uniswap", "token": "UNI", "intro": "Decentralized exchange protocol", "links": [{"title": "Website", "url": "https://uniswap.org/"}, {"title": "Twitter", "url": "Uniswap"}, {"title": "Discord", "url": "https://discord.gg/FCfyBSbCU5"}, {"title": "Github", "url": "https://github.com/Uniswap"}, {"title": "Snapshot", "url": "https://snapshot.org/#/uniswap"}, {"title": "CMC", "url": "https://coinmarketcap.com/currencies/uniswap/"}], "introduce": "The Uniswap is an decentralized exchange\u00a0protocol for providing liquidity and trading tokens. It eliminates trusted intermediaries and unnecessary forms of rent extraction, allowing for safe, accessible, and efficient exchange activity."}