{"name": "Zenlink", "token": "ZLK", "intro": "Cross-chain DEX protocol", "links": [{"title": "Website", "url": "https://zenlink.pro/"}, {"title": "Twitter", "url": "ZenlinkPro"}, {"title": "Telegram", "url": "https://t.me/ZenlinkPro_EN"}, {"title": "Github", "url": "https://github.com/zenlinkpro/"}, {"title": "White Paper", "url": "https://github.com/zenlinkpro/whitepaper"}, {"title": "Medium", "url": "https://medium.com/zenlinkPro"}, {"title": "CMC", "url": "https://coinmarketcap.com/currencies/zenlink/"}], "introduce": "Zenlink is an underlying cross-chain DEX protocol based on Polkadot and is committed to becoming the DEX composable hub of Polkadot. By accessing the ultimate, open, and universal cross-chain DEX protocol based on Substrate, Zenlink DEX Protocol enables all parachains to build DEX and achieve liquidity sharing in one click. Zenlink DEX Protocol includes Module, WASM, and EVM implementations, which are flexible and adaptable, allowing for customizable compositions and interoperability with different DeFi modules. In addition, the Zenlink DEX Aggregator connects all DEX DApps on Polkadot and aggregates liquidity, providing users low slippage trading experience."}