{"name": "Hundred Finance", "token": "HND", "intro": "Decentralized borrowing and lending protocol", "links": [{"title": "Website", "url": "https://hundred.finance/"}, {"title": "Twitter", "url": "HundredFinance"}, {"title": "Discord", "url": "https://discord.com/invite/phK668J6dQ"}, {"title": "Github", "url": "https://github.com/hundred-finance"}, {"title": "Medium", "url": "https://hundred-finance.medium.com/"}, {"title": "CMC", "url": "https://coinmarketcap.com/currencies/hundred-finance/"}], "introduce": "Hundred Finance is a decentralized application (dApp) that enables the lending and borrowing of cryptocurrencies. A multi-chain protocol, it integrates vote-escrow tokenomics in the cross-chain management of protocol governance and incorporates Chainlink oracles for system health and stability in its provision of markets for long-tail crypto assets."}