{"name": "EdgeSwap", "token": "EGS", "intro": "Ethereum-based layer 2 trading protocol", "links": [{"title": "Website", "url": "https://www.edgeswap.io/"}, {"title": "Twitter", "url": "EdgeSwap"}, {"title": "Discord", "url": "https://discord.com/invite/5bPdntHbvz"}, {"title": "Telegram", "url": "https://t.me/EdgeSwap"}, {"title": "Github", "url": "https://github.com/EdgeSwap"}, {"title": "Medium", "url": "https://medium.com/@EdgeSwap"}, {"title": "CMC", "url": "https://coinmarketcap.com/currencies/edgeswap/"}], "introduce": "EdgeSwap is an Ethereum-based layer 2 trading protocol that adopts the ZK Rollup technology. With the industry\u2019s top-grade hardware acceleration solution and circuit optimization system, EdgeSwap provides the market with high-performance, cost-effective swapping and farming services."}