{"name": "COINZIX", "token": null, "intro": "Cryptocurrency exchange", "links": [{"title": "Website", "url": "https://coinzix.com/"}, {"title": "Twitter", "url": "coinzixcom"}, {"title": "Telegram", "url": "https://t.me/coinzixCEX"}, {"title": "Blog", "url": "https://blog.coinzix.com/"}], "introduce": "COINZIX is a cryptocurrency exchange that operates primarily within the European market. With over 60 crypto assets in its offer, COINZIX allows users to trade via bank transfer, debit card, and much more, offering seamless mobile and desktop experiences."}