{"name": "Arianee", "token": null, "intro": "NFT solution built to create, distribute and interact with NFTs", "links": [{"title": "Website", "url": "https://www.arianee.org/"}, {"title": "Twitter", "url": "ArianeeProject"}, {"title": "LinkedIn", "url": "http://www.linkedin.com/company/arianee/"}], "introduce": "Arianee is an NFT solution built to create, distribute and interact with NFTs. The platform and products enable brands to tokenize, distribute and leverage value through NFTs. Arianee's SaaS platform allows brands to create enriched NFTs packed with exclusive and unique features (Airdrop claim, CRM, time-stamping, transparency, AR, metaverse deployment, etc) and distribute them to all kinds of audiences, from physical to digital redeem, from claim to drop, free to auction.\nArianee's architecture has been built to fit the integration needs of enterprises\u2019 information systems and its end user interface solutions are designed to be fully embedded within each brand's user journeys with white label and SDK options."}