{"name": "Kenshi", "token": null, "intro": "Full-stack application development platform targeting blockchains", "links": [{"title": "Website", "url": "https://kenshi.io/"}, {"title": "Twitter", "url": "KenshiTech"}, {"title": "Discord", "url": "https://discord.gg/KenshiTech"}, {"title": "Telegram", "url": "https://t.me/KenshiTech"}, {"title": "Medium", "url": "https://blog.kenshi.io/"}], "introduce": "Kenshi is a full-stack application development platform targeting blockchains. Kenshi enables fast product development and reduces time to market. Whether developers want to index and query blockchain data or deliver data to the blockchain, Kenshi has them covered by enabling two-way communication."}